clud_central/__init__.py
clud_central/cli.py
clud_central/assets/example.txt
clud_central-0.0.1.dist-info/licenses/LICENSE
clud_central-0.0.1.dist-info/METADATA
clud_central-0.0.1.dist-info/WHEEL
clud_central-0.0.1.dist-info/entry_points.txt
clud_central-0.0.1.dist-info/top_level.txt
clud_central-0.0.1.dist-info/RECORD
