Metadata-Version: 2.4
Name: clud_central
Version: 0.0.1
Summary: aggregotor of clud clients
Home-page: 
Maintainer: Zachary Vorhies
License: BSD 3-Clause License
Keywords: template-python-cmd
Classifier: Programming Language :: Python :: 3
Requires-Python: >=3.10
License-File: LICENSE
Dynamic: license-file
Dynamic: maintainer
